[{"en":"accounting","pt":"contabilidade","es":"contabilidad"},{"en":"airlines\/aviation","pt":"companhias a\u00e9reas\/avia\u00e7\u00e3o","es":"aerol\u00edneas\/aviaci\u00f3n"},{"en":"alternative dispute resolution","pt":"resolu\u00e7\u00e3o alternativa de disputa","es":"resoluci\u00f3n de conflicto alternativa"},{"en":"alternative medicine","pt":"medicina alternativa","es":"medicina alternativa"},{"en":"animation","pt":"anima\u00e7\u00e3o","es":"animaci\u00f3n"},{"en":"apparel & fashion","pt":"vestu\u00e1rio e moda","es":"ropa y moda"},{"en":"architecture & planning","pt":"arquitetura e planejamento","es":"arquitectura y planificaci\u00f3n"},{"en":"arts & crafts","pt":"artes e of\u00edcios","es":"arte y artesan\u00eda"},{"en":"automotive","pt":"automotivo","es":"automotor"},{"en":"aviation & aerospace","pt":"avia\u00e7\u00e3o e aeroespacial","es":"aviaci\u00f3n y aeroespacial"},{"en":"banking","pt":"banc\u00e1rio","es":"bancario"},{"en":"biotechnology","pt":"biotecnologia","es":"biotecnolog\u00eda"},{"en":"broadcast media","pt":"m\u00eddia de transmiss\u00e3o","es":"medios de difusi\u00f3n"},{"en":"building materials","pt":"materiais de constru\u00e7\u00e3o","es":"materiales de construcci\u00f3n"},{"en":"business supplies & equipment","pt":"suprimentos e equipamentos comerciais","es":"suministros y equipos comerciales"},{"en":"capital markets","pt":"mercados capitais","es":"los mercados de capitales"},{"en":"chemicals","pt":"produtos qu\u00edmicos","es":"quimicos"},{"en":"civic & social organization","pt":"organiza\u00e7\u00e3o c\u00edvica e social","es":"organizaci\u00f3n c\u00edvica y social"},{"en":"civil engineering","pt":"engenharia civil","es":"ingenier\u00eda civil"},{"en":"commercial real estate","pt":"im\u00f3veis comerciais","es":"bienes ra\u00edces comerciales"},{"en":"computer & network security","pt":"seguran\u00e7a de computadores e redes","es":"seguridad inform\u00e1tica y de redes"},{"en":"computer games","pt":"jogos de computador","es":"juegos de computadora"},{"en":"computer hardware","pt":"hardware de computador","es":"hardware de la computadora"},{"en":"computer networking","pt":"redes de computadores","es":"redes de computadoras"},{"en":"computer software","pt":"software de computador","es":"software de ordenador"},{"en":"construction","pt":"constru\u00e7\u00e3o","es":"construcci\u00f3n"},{"en":"consumer electronics","pt":"eletr\u00f4nicos de consumo","es":"electr\u00f3nica de consumo"},{"en":"consumer goods","pt":"bens de consumo","es":"bienes de consumo"},{"en":"consumer services","pt":"servi\u00e7os do consumidor","es":"servicio al consumidor"},{"en":"cosmetics","pt":"cosm\u00e9ticos","es":"productos cosm\u00e9ticos"},{"en":"dairy","pt":"latic\u00ednio","es":"l\u00e1cteos"},{"en":"defense & space","pt":"defesa e espa\u00e7o","es":"defensa y espacio"},{"en":"design","pt":"projeto","es":"dise\u00f1o"},{"en":"education management","pt":"gerenciamento de educa\u00e7\u00e3o","es":"administraci\u00f3n de educaci\u00f3n"},{"en":"e-learning","pt":"e-learning","es":"aprendizaje electr\u00f3nico"},{"en":"electrical & electronic manufacturing","pt":"fabrica\u00e7\u00e3o el\u00e9trica e eletr\u00f4nica","es":"fabricaci\u00f3n el\u00e9ctrica y electr\u00f3nica"},{"en":"entertainment","pt":"entretenimento","es":"entretenimiento"},{"en":"environmental services","pt":"servi\u00e7os ambientais","es":"servicios ambientales"},{"en":"events services","pt":"servi\u00e7os de eventos","es":"servicios de eventos"},{"en":"executive office","pt":"escrit\u00f3rio executivo","es":"oficina ejecutiva"},{"en":"facilities services","pt":"servi\u00e7os de instala\u00e7\u00f5es","es":"servicios de instalaciones"},{"en":"farming","pt":"agricultura","es":"agricultura"},{"en":"financial services","pt":"servi\u00e7os financeiros","es":"servicios financieros"},{"en":"fine art","pt":"belas artes","es":"arte fino"},{"en":"fishery","pt":"pesca","es":"pesquer\u00eda"},{"en":"food & beverages","pt":"alimentos e bebidas","es":"alimentos y bebidas"},{"en":"food production","pt":"produ\u00e7\u00e3o de alimentos","es":"la producci\u00f3n de alimentos"},{"en":"fundraising","pt":"angaria\u00e7\u00e3o de fundos","es":"recaudaci\u00f3n de fondos"},{"en":"furniture","pt":"mob\u00edlia","es":"muebles"},{"en":"gambling & casinos","pt":"jogos de azar e cassinos","es":"juegos de azar y casinos"},{"en":"glass, ceramics & concrete","pt":"vidro, cer\u00e2mica e concreto","es":"vidrio, cer\u00e1mica y hormig\u00f3n"},{"en":"government administration","pt":"administra\u00e7\u00e3o governamental","es":"administraci\u00f3n gubernamental"},{"en":"government relations","pt":"rela\u00e7\u00f5es governamentais","es":"relaciones gubernamentales"},{"en":"graphic design","pt":"design gr\u00e1fico","es":"dise\u00f1o gr\u00e1fico"},{"en":"health, wellness & fitness","pt":"sa\u00fade, bem-estar e boa forma","es":"salud, bienestar y fitness"},{"en":"higher education","pt":"ensino superior","es":"educaci\u00f3n m\u00e1s alta"},{"en":"hospital & health care","pt":"hospitais e cuidados de sa\u00fade","es":"atenci\u00f3n sanitaria y hospitalaria"},{"en":"hospitality","pt":"hospitalidade","es":"hospitalidad"},{"en":"human resources","pt":"recursos humanos","es":"recursos humanos"},{"en":"import & export","pt":"importar e exportar","es":"importaci\u00f3n y exportaci\u00f3n"},{"en":"individual & family services","pt":"servi\u00e7os individuais e familiares","es":"servicios individuales y familiares"},{"en":"industrial automation","pt":"automa\u00e7\u00e3o industrial","es":"automatizaci\u00f3n industrial"},{"en":"information services","pt":"servi\u00e7os de informa\u00e7\u00e3o","es":"servicios de informaci\u00f3n"},{"en":"information technology & services","pt":"tecnologia da informa\u00e7\u00e3o e servi\u00e7os","es":"servicios y tecnolog\u00eda de la informaci\u00f3n"},{"en":"insurance","pt":"seguro","es":"seguro"},{"en":"international affairs","pt":"assuntos internacionais","es":"asuntos internacionales"},{"en":"international trade & development","pt":"com\u00e9rcio internacional e desenvolvimento","es":"comercio internacional y desarrollo"},{"en":"internet","pt":"internet","es":"internet"},{"en":"investment banking\/venture","pt":"banco de investimento\/empreendimento","es":"banca de inversi\u00f3n\/riesgo"},{"en":"investment management","pt":"gest\u00e3o de investimentos","es":"gesti\u00f3n de inversiones"},{"en":"judiciary","pt":"judici\u00e1rio","es":"judicial"},{"en":"law enforcement","pt":"aplica\u00e7\u00e3o da lei","es":"cumplimiento de la ley"},{"en":"law practice","pt":"pr\u00e1tica de direito","es":"pr\u00e1ctica jur\u00eddica"},{"en":"legal services","pt":"servi\u00e7os legais","es":"servicios legales"},{"en":"legislative office","pt":"gabinete legislativo","es":"oficina legislativa"},{"en":"leisure & travel","pt":"viagem de lazer","es":"viaje de placer"},{"en":"libraries","pt":"bibliotecas","es":"bibliotecas"},{"en":"logistics & supply chain","pt":"log\u00edstica e cadeia de suprimentos","es":"log\u00edstica y cadena de suministro"},{"en":"luxury goods & jewelry","pt":"bens de luxo e joias","es":"art\u00edculos de lujo y joyer\u00eda"},{"en":"machinery","pt":"m\u00e1quinas","es":"maquinaria"},{"en":"management consulting","pt":"consultoria de gest\u00e3o","es":"consultor\u00eda de gesti\u00f3n"},{"en":"maritime","pt":"mar\u00edtimo","es":"mar\u00edtimo"},{"en":"marketing & advertising","pt":"marketing e publicidade","es":"anuncios de marketing"},{"en":"market research","pt":"pesquisa de mercado","es":"investigaci\u00f3n de mercado"},{"en":"mechanical or industrial engineering","pt":"engenharia mec\u00e2nica ou industrial","es":"ingenier\u00eda industrial o mec\u00e1nica"},{"en":"media production","pt":"produ\u00e7\u00e3o da m\u00eddia","es":"producci\u00f3n de medios"},{"en":"medical device","pt":"aparelho m\u00e9dico","es":"dispositivo m\u00e9dico"},{"en":"medical practice","pt":"pr\u00e1tica m\u00e9dica","es":"pr\u00e1ctica m\u00e9dica"},{"en":"mental health care","pt":"cuidados de sa\u00fade mental","es":"cuidado de la salud mental"},{"en":"military","pt":"militares","es":"militar"},{"en":"mining & metals","pt":"minera\u00e7\u00e3o e metais","es":"miner\u00eda y metales"},{"en":"motion pictures & film","pt":"filmes e filmes","es":"pel\u00edculas y pel\u00edculas"},{"en":"museums & institutions","pt":"museus e institui\u00e7\u00f5es","es":"museos e instituciones"},{"en":"music","pt":"m\u00fasica","es":"m\u00fasica"},{"en":"nanotechnology","pt":"nanotecnologia","es":"nanotecnolog\u00eda"},{"en":"newspapers","pt":"jornais","es":"peri\u00f3dicos"},{"en":"nonprofit organization management","pt":"gest\u00e3o de organiza\u00e7\u00f5es sem fins lucrativos","es":"gesti\u00f3n de organizaciones sin fines de lucro"},{"en":"oil & energy","pt":"petr\u00f3leo e energia","es":"petr\u00f3leo y energ\u00eda"},{"en":"online publishing","pt":"publica\u00e7\u00e3o on-line","es":"publicaci\u00f3n en l\u00ednea"},{"en":"outsourcing\/offshoring","pt":"terceiriza\u00e7\u00e3o\/offshore","es":"subcontrataci\u00f3n\/deslocalizaci\u00f3n"},{"en":"package\/freight delivery","pt":"entrega de pacote\/frete","es":"entrega de paquetes\/carga"},{"en":"packaging & containers","pt":"embalagens e recipientes","es":"embalajes y contenedores"},{"en":"paper & forest products","pt":"papel e produtos florestais","es":"productos de papel y forestales"},{"en":"performing arts","pt":"artes perform\u00e1ticas","es":"las artes esc\u00e9nicas"},{"en":"pharmaceuticals","pt":"produtos farmac\u00eauticos","es":"productos farmac\u00e9uticos"},{"en":"philanthropy","pt":"filantropia","es":"filantrop\u00eda"},{"en":"photography","pt":"fotografia","es":"fotograf\u00eda"},{"en":"plastics","pt":"pl\u00e1sticos","es":"pl\u00e1stica"},{"en":"political organization","pt":"organiza\u00e7\u00e3o pol\u00edtica","es":"organizaci\u00f3n pol\u00edtica"},{"en":"primary\/secondary","pt":"prim\u00e1rio secund\u00e1rio","es":"primario secundario"},{"en":"printing","pt":"impress\u00e3o","es":"impresi\u00f3n"},{"en":"professional training","pt":"treinamento profissional","es":"entrenamiento profesional"},{"en":"program development","pt":"desenvolvimento de programa","es":"desarrollo del programa"},{"en":"public policy","pt":"pol\u00edticas p\u00fablicas","es":"pol\u00edtica p\u00fablica"},{"en":"public relations","pt":"rela\u00e7\u00f5es p\u00fablicas","es":"relaciones p\u00fablicas"},{"en":"public safety","pt":"seguran\u00e7a p\u00fablica","es":"seguridad p\u00fablica"},{"en":"publishing","pt":"publica\u00e7\u00e3o","es":"publicaci\u00f3n"},{"en":"railroad manufacture","pt":"fabrica\u00e7\u00e3o ferrovi\u00e1ria","es":"fabricaci\u00f3n de ferrocarriles"},{"en":"ranching","pt":"pecu\u00e1ria","es":"ganader\u00eda"},{"en":"real estate","pt":"imobili\u00e1ria","es":"bienes ra\u00edces"},{"en":"recreational","pt":"recreativo","es":"recreativo"},{"en":"facilities & services","pt":"servi\u00e7os de instala\u00e7\u00f5es","es":"instalaciones y servicios"},{"en":"religious institutions","pt":"institui\u00e7\u00f5es religiosas","es":"instituciones religiosas"},{"en":"renewables & environment","pt":"energias renov\u00e1veis \u200b\u200be meio ambiente","es":"energ\u00edas renovables y medio ambiente"},{"en":"research","pt":"pesquisar","es":"investigaci\u00f3n"},{"en":"restaurants","pt":"restaurantes","es":"restaurantes"},{"en":"retail","pt":"varejo","es":"minorista"},{"en":"security & investigations","pt":"seguran\u00e7a e investiga\u00e7\u00f5es","es":"seguridad e investigaciones"},{"en":"semiconductors","pt":"semicondutores","es":"semiconductores"},{"en":"shipbuilding","pt":"constru\u00e7\u00e3o naval","es":"construcci\u00f3n naval"},{"en":"sporting goods","pt":"artigos esportivos","es":"art\u00edculos deportivos"},{"en":"sports","pt":"esportes","es":"deportes"},{"en":"staffing & recruiting","pt":"pessoal e recrutamento","es":"dotaci\u00f3n de personal y reclutamiento"},{"en":"supermarkets","pt":"supermercados","es":"supermercados"},{"en":"telecommunications","pt":"telecomunica\u00e7\u00f5es","es":"telecomunicaciones"},{"en":"textiles","pt":"t\u00eaxteis","es":"textiles"},{"en":"think tanks","pt":"grupos de reflex\u00e3o","es":"think tanks"},{"en":"tobacco","pt":"tabaco","es":"tabaco"},{"en":"translation & localization","pt":"tradu\u00e7\u00e3o e localiza\u00e7\u00e3o","es":"traducci\u00f3n y localizaci\u00f3n"},{"en":"transportation\/trucking\/railroad","pt":"transporte\/caminh\u00f5es\/ferrovia","es":"transporte\/camiones\/ferrocarril"},{"en":"utilities","pt":"servi\u00e7os de utilidade p\u00fablica","es":"utilidades"},{"en":"venture capital","pt":"capital de risco","es":"capital de riesgo"},{"en":"veterinary","pt":"veterin\u00e1rio","es":"veterinario"},{"en":"warehousing","pt":"armazenagem","es":"almacenamiento"},{"en":"wholesale","pt":"atacado","es":"venta al por mayor"},{"en":"wine & spirits","pt":"vinho e destilados","es":"vinos y licores"},{"en":"wireless","pt":"sem fio","es":"inal\u00e1mbrico"},{"en":"writing & editing","pt":"escrita e edi\u00e7\u00e3o","es":"escritura y edici\u00f3n"}]